{
  "videos": [
    {
      "section": "winter",
      "name": "Зима",
      "listVideo": [
        {
          "id_video": 1,
          "link": "https://www.youtube.com/embed/Aodi_1t-iuM",
          "name": "Зайчики прыгают на утреннике"
        },
        {
          "id_video": 2,
          "link": "https://www.youtube.com/embed/Aodi_1t-iuM",
          "name": "Зайчики прыгают на утреннике"
        }
      ]
    },
    {
      "section": "exam",
      "name": "Экзамен",
      "listVideo": [
        {
          "id_video": 3,
          "link": "https://www.youtube.com/embed/MN2jB-5uhZc",
          "name": "Ведмеди прыгают на утреннике"
        },
        {
          "id_video": 4,
          "link": "https://www.youtube.com/embed/MN2jB-5uhZc",
          "name": "Ведмеди прыгают на утреннике"
        },
        {
          "id_video": 5,
          "link": "https://www.youtube.com/embed/MN2jB-5uhZc",
          "name": "Ведмеди прыгают на утреннике"
        }
      ]
    }
  ]
}